napari_j/__init__.py
napari_j/_dock_widget.py
napari_j/bridge.py
napari_j/connection.py
napari_j/image.py
napari_j/napari.yaml
napari_j/points.py
napari_j/_tests/__init__.py
napari_j/_tests/bridge_unit_test.py
napari_j/_tests/test_dock_widget.py
napari_j/_tests/surrogate/.gitignore
napari_j/_tests/surrogate/README.rst
napari_j/_tests/surrogate/__init__ (copy).py
napari_j/_tests/surrogate/__init__.py
napari_j/_tests/surrogate/surrogate.py
napari_J-0.3.dist-info/LICENSE
napari_J-0.3.dist-info/METADATA
napari_J-0.3.dist-info/WHEEL
napari_J-0.3.dist-info/entry_points.txt
napari_J-0.3.dist-info/top_level.txt
napari_J-0.3.dist-info/RECORD
