Metadata-Version: 2.1
Name: napari-J
Version: 0.3
Summary: A plugin to exchange data with FIJI and to use FIJI image analysis from napari
Home-page: https://github.com/MontpellierRessourcesImagerie/napari-J
Author: Volker Baecker
Author-email: volker.baecker@mri.cnrs.fr
License: MIT
Project-URL: Bug Tracker, https://github.com/MontpellierRessourcesImagerie/napari-J/issues
Project-URL: Documentation, https://github.com/MontpellierRessourcesImagerie/napari-J#README.md
Project-URL: Source Code, https://github.com/MontpellierRessourcesImagerie/napari-J
Project-URL: User Support, https://github.com/MontpellierRessourcesImagerie/napari-J/issues
Classifier: Development Status :: 4 - Beta
Classifier: Intended Audience :: Science/Research
Classifier: Topic :: Scientific/Engineering
Classifier: License :: OSI Approved :: MIT License
Classifier: Operating System :: OS Independent
Classifier: Programming Language :: Python :: 3.7
Classifier: Programming Language :: Python :: 3.8
Classifier: Programming Language :: Python :: 3.9
Classifier: Framework :: napari
Requires-Python: >=3.7
License-File: LICENSE
Requires-Dist: JPype1 (>=1.2.1)
Requires-Dist: matplotlib
Requires-Dist: imageio-ffmpeg
Provides-Extra: testing
Requires-Dist: matplotlib ; extra == 'testing'
Requires-Dist: imageio-ffmpeg ; extra == 'testing'
Requires-Dist: python-matplotlib-qt5 ; extra == 'testing'
Requires-Dist: pytest-qt ; extra == 'testing'
